CHANGES.txt
README.txt
setup.py
src/gocept/__init__.py
src/gocept.cvs.egg-info/PKG-INFO
src/gocept.cvs.egg-info/SOURCES.txt
src/gocept.cvs.egg-info/dependency_links.txt
src/gocept.cvs.egg-info/entry_points.txt
src/gocept.cvs.egg-info/namespace_packages.txt
src/gocept.cvs.egg-info/not-zip-safe
src/gocept.cvs.egg-info/requires.txt
src/gocept.cvs.egg-info/top_level.txt
src/gocept/cvs/__init__.py
src/gocept/cvs/tests/README.txt
src/gocept/cvs/tests/__init__.py
src/gocept/cvs/tests/cvsrep.py
src/gocept/cvs/tests/tags.txt
src/gocept/cvs/tests/test_recipe.py
src/gocept/cvs/tests/testdata/.cvsignore
src/gocept/cvs/tests/testdata/file
