Metadata-Version: 1.0
Name: gocept.cvs
Version: 0.1.9
Summary: zc.buildout recipe for checking out cvs modules.
Home-page: http://svn.gocept.com/repos/gocept/gocept.cvs
Author: Daniel Havlik
Author-email: dh@gocept.com
License: ZPL 2.1
Download-URL: https://svn.gocept.com/repos/gocept/gocept.cvs/trunk#egg=gocept.cvs-dev
Keywords: buildout cvs recipe
Platform: UNKNOWN
Classifier: Framework :: Buildout
